{"startedAt":"2024-12-02T03:19:24.002Z","endpoints":[{"url":"https://poisonpie.us-west.host.bsky.network","createdAt":"2024-12-02T06:47:20.266Z"},{"url":"https://fibercap.us-west.host.bsky.network","createdAt":"2024-12-02T06:47:20.123Z"},{"url":"https://blusher.us-east.host.bsky.network","createdAt":"2024-12-02T06:47:19.994Z"},{"url":"https://morel.us-east.host.bsky.network","createdAt":"2024-12-02T06:47:18.988Z"},{"url":"https://brittlegill.us-west.host.bsky.network","createdAt":"2024-12-02T06:47:17.759Z"},{"url":"https://yellowfoot.us-west.host.bsky.network","createdAt":"2024-12-02T06:47:15.343Z"},{"url":"https://velvetfoot.us-east.host.bsky.network","createdAt":"2024-12-02T06:45:35.271Z"},{"url":"https://shaggymane.us-west.host.bsky.network","createdAt":"2024-12-02T06:45:30.802Z"},{"url":"https://truffle.us-east.host.bsky.network","createdAt":"2024-12-02T06:45:29.924Z"},{"url":"https://panthercap.us-east.host.bsky.network","createdAt":"2024-12-02T06:44:21.473Z"},{"url":"https://woodear.us-west.host.bsky.network","createdAt":"2024-12-02T06:44:02.976Z"},{"url":"https://reishi.us-east.host.bsky.network","createdAt":"2024-12-02T06:41:57.746Z"},{"url":"https://bracket.us-west.host.bsky.network","createdAt":"2024-12-02T06:41:29.297Z"},{"url":"https://scarletina.us-east.host.bsky.network","createdAt":"2024-12-02T06:39:20.598Z"},{"url":"https://porcini.us-east.host.bsky.network","createdAt":"2024-12-02T06:38:50.672Z"},{"url":"https://cremini.us-west.host.bsky.network","createdAt":"2024-12-02T06:38:49.824Z"},{"url":"https://helvella.us-east.host.bsky.network","createdAt":"2024-12-02T06:38:01.740Z"},{"url":"https://enoki.us-east.host.bsky.network","createdAt":"2024-12-02T06:37:40.935Z"},{"url":"https://button.us-west.host.bsky.network","createdAt":"2024-12-02T06:37:02.807Z"},{"url":"https://gomphus.us-west.host.bsky.network","createdAt":"2024-12-02T06:36:41.412Z"},{"url":"https://cordyceps.us-west.host.bsky.network","createdAt":"2024-12-02T06:36:39.895Z"},{"url":"https://meadow.us-east.host.bsky.network","createdAt":"2024-12-02T06:36:27.405Z"},{"url":"https://chaga.us-west.host.bsky.network","createdAt":"2024-12-02T06:36:24.842Z"},{"url":"https://lionsmane.us-east.host.bsky.network","createdAt":"2024-12-02T06:36:10.812Z"},{"url":"https://splitgill.us-east.host.bsky.network","createdAt":"2024-12-02T06:36:04.685Z"},{"url":"https://amanita.us-east.host.bsky.network","createdAt":"2024-12-02T06:35:30.614Z"},{"url":"https://agaric.us-west.host.bsky.network","createdAt":"2024-12-02T06:35:26.960Z"},{"url":"https://boletus.us-west.host.bsky.network","createdAt":"2024-12-02T06:35:19.215Z"},{"url":"https://oyster.us-east.host.bsky.network","createdAt":"2024-12-02T06:34:59.934Z"},{"url":"https://shimeji.us-east.host.bsky.network","createdAt":"2024-12-02T06:33:59.332Z"},{"url":"https://lobster.us-east.host.bsky.network","createdAt":"2024-12-02T06:33:47.614Z"},{"url":"https://milkcap.us-west.host.bsky.network","createdAt":"2024-12-02T06:33:05.965Z"},{"url":"https://witchesbutter.us-west.host.bsky.network","createdAt":"2024-12-02T06:33:00.842Z"},{"url":"https://maitake.us-west.host.bsky.network","createdAt":"2024-12-02T06:31:35.353Z"},{"url":"https://ganoderma.us-west.host.bsky.network","createdAt":"2024-12-02T06:29:41.011Z"},{"url":"https://shiitake.us-east.host.bsky.network","createdAt":"2024-12-02T06:29:00.139Z"},{"url":"https://lepista.us-west.host.bsky.network","createdAt":"2024-12-02T06:28:17.524Z"},{"url":"https://earthstar.us-east.host.bsky.network","createdAt":"2024-12-02T06:26:54.053Z"},{"url":"https://coral.us-east.host.bsky.network","createdAt":"2024-12-02T06:23:56.300Z"},{"url":"https://inkcap.us-east.host.bsky.network","createdAt":"2024-12-02T06:20:37.983Z"},{"url":"https://hydnum.us-west.host.bsky.network","createdAt":"2024-12-02T06:19:01.104Z"},{"url":"https://blewit.us-west.host.bsky.network","createdAt":"2024-12-02T06:17:26.177Z"},{"url":"https://parasol.us-east.host.bsky.network","createdAt":"2024-12-02T06:16:50.635Z"},{"url":"https://stinkhorn.us-west.host.bsky.network","createdAt":"2024-12-02T06:16:36.811Z"},{"url":"https://puffball.us-east.host.bsky.network","createdAt":"2024-12-02T06:15:58.458Z"},{"url":"https://chanterelle.us-west.host.bsky.network","createdAt":"2024-12-02T06:15:00.024Z"},{"url":"https://matsutake.us-west.host.bsky.network","createdAt":"2024-12-02T05:58:14.910Z"},{"url":"https://russula.us-west.host.bsky.network","createdAt":"2024-12-02T05:57:49.979Z"},{"url":"https://conocybe.us-west.host.bsky.network","createdAt":"2024-12-02T05:45:52.240Z"},{"url":"https://magic.us-west.host.bsky.network","createdAt":"2024-12-02T05:45:40.688Z"},{"url":"https://verpa.us-west.host.bsky.network","createdAt":"2024-12-02T05:00:53.181Z"},{"url":"https://bluesky.aviate.org","createdAt":"2024-12-02T06:43:31.499Z","alive":true,"inviteCodeRequired":true,"phoneVerificationRequired":false},{"url":"https://atproto.brid.gy","createdAt":"2024-12-02T06:42:22.969Z","alive":true,"inviteCodeRequired":false,"phoneVerificationRequired":false},{"url":"https://pds.shaggylabs.com","createdAt":"2024-12-02T05:53:41.742Z","alive":true,"inviteCodeRequired":true,"phoneVerificationRequired":false},{"url":"https://blueskypds.readprologue.com","createdAt":"2024-12-02T05:46:19.327Z","alive":false},{"url":"https://elusivor.asuscomm.com","createdAt":"2024-12-02T05:38:06.868Z","alive":false},{"url":"https://yashas.social","createdAt":"2024-12-02T05:29:44.886Z","alive":true,"inviteCodeRequired":false,"phoneVerificationRequired":false},{"url":"https://sparrowrayne.com","createdAt":"2024-12-02T05:20:03.976Z","alive":true,"inviteCodeRequired":true,"phoneVerificationRequired":false},{"url":"https://lamp.wtf","createdAt":"2024-12-02T05:12:23.136Z","alive":true,"inviteCodeRequired":true,"phoneVerificationRequired":false},{"url":"https://bluesky.home.notquite.me","createdAt":"2024-12-02T04:40:56.370Z","alive":true,"inviteCodeRequired":true,"phoneVerificationRequired":false},{"url":"https://rat.mom","createdAt":"2024-12-02T03:49:56.601Z","alive":true,"inviteCodeRequired":true,"phoneVerificationRequired":false},{"url":"https://zio.blue","createdAt":"2024-12-02T03:37:28.434Z","alive":true,"inviteCodeRequired":true,"phoneVerificationRequired":false},{"url":"https://bsky.haworth.id.au","createdAt":"2024-12-02T03:22:57.027Z","alive":true,"inviteCodeRequired":true,"phoneVerificationRequired":false}]}