{"startedAt":"2025-10-03T03:11:25.117Z","endpoints":[{"url":"https://calocybe.us-west.host.bsky.network","createdAt":"2025-10-03T09:26:21.189Z"},{"url":"https://rhizopogon.us-west.host.bsky.network","createdAt":"2025-10-03T09:26:10.888Z"},{"url":"https://hebeloma.us-west.host.bsky.network","createdAt":"2025-10-03T09:26:10.578Z"},{"url":"https://entoloma.us-west.host.bsky.network","createdAt":"2025-10-03T09:26:09.111Z"},{"url":"https://phellinus.us-west.host.bsky.network","createdAt":"2025-10-03T09:25:58.994Z"},{"url":"https://hygrophorus.us-west.host.bsky.network","createdAt":"2025-10-03T09:25:49.373Z"},{"url":"https://pholiota.us-west.host.bsky.network","createdAt":"2025-10-03T09:25:42.142Z"},{"url":"https://gomphidius.us-west.host.bsky.network","createdAt":"2025-10-03T09:25:34.627Z"},{"url":"https://leccinum.us-west.host.bsky.network","createdAt":"2025-10-03T09:25:30.175Z"},{"url":"https://discina.us-west.host.bsky.network","createdAt":"2025-10-03T09:25:28.589Z"},{"url":"https://agrocybe.us-west.host.bsky.network","createdAt":"2025-10-03T09:25:01.158Z"},{"url":"https://chalciporus.us-west.host.bsky.network","createdAt":"2025-10-03T09:24:27.877Z"},{"url":"https://cortinarius.us-west.host.bsky.network","createdAt":"2025-10-03T09:24:27.849Z"},{"url":"https://morel.us-east.host.bsky.network","createdAt":"2025-10-03T09:24:19.675Z"},{"url":"https://bankera.us-west.host.bsky.network","createdAt":"2025-10-03T09:24:13.154Z"},{"url":"https://auriporia.us-west.host.bsky.network","createdAt":"2025-10-03T09:23:39.485Z"},{"url":"https://polypore.us-west.host.bsky.network","createdAt":"2025-10-03T09:23:05.755Z"},{"url":"https://mycena.us-west.host.bsky.network","createdAt":"2025-10-03T09:19:37.178Z"},{"url":"https://hollowfoot.us-west.host.bsky.network","createdAt":"2025-10-03T09:18:03.108Z"},{"url":"https://hydnum.us-west.host.bsky.network","createdAt":"2025-10-03T09:12:52.242Z"},{"url":"https://lionsmane.us-east.host.bsky.network","createdAt":"2025-10-03T09:11:14.844Z"},{"url":"https://porcini.us-east.host.bsky.network","createdAt":"2025-10-03T09:09:38.177Z"},{"url":"https://helvella.us-east.host.bsky.network","createdAt":"2025-10-03T09:09:23.986Z"},{"url":"https://fuzzyfoot.us-west.host.bsky.network","createdAt":"2025-10-03T09:08:10.791Z"},{"url":"https://ganoderma.us-west.host.bsky.network","createdAt":"2025-10-03T09:06:18.975Z"},{"url":"https://mazegill.us-west.host.bsky.network","createdAt":"2025-10-03T09:05:49.023Z"},{"url":"https://lobster.us-east.host.bsky.network","createdAt":"2025-10-03T09:04:30.174Z"},{"url":"https://dapperling.us-west.host.bsky.network","createdAt":"2025-10-03T08:55:46.387Z"},{"url":"https://oysterling.us-west.host.bsky.network","createdAt":"2025-10-03T08:54:35.822Z"},{"url":"https://pioppino.us-west.host.bsky.network","createdAt":"2025-10-03T08:53:23.952Z"},{"url":"https://panus.us-west.host.bsky.network","createdAt":"2025-10-03T08:48:36.534Z"},{"url":"https://oyster.us-east.host.bsky.network","createdAt":"2025-10-03T08:38:02.058Z"},{"url":"https://verpa.us-west.host.bsky.network","createdAt":"2025-10-03T08:31:16.413Z"},{"url":"https://shiitake.us-east.host.bsky.network","createdAt":"2025-10-03T08:29:22.837Z"},{"url":"https://maitake.us-west.host.bsky.network","createdAt":"2025-10-03T08:24:18.291Z"},{"url":"https://chanterelle.us-west.host.bsky.network","createdAt":"2025-10-03T08:22:01.354Z"},{"url":"https://conocybe.us-west.host.bsky.network","createdAt":"2025-10-03T08:16:32.635Z"},{"url":"https://parasol.us-east.host.bsky.network","createdAt":"2025-10-03T08:13:38.772Z"},{"url":"https://agaric.us-west.host.bsky.network","createdAt":"2025-10-03T08:11:10.806Z"},{"url":"https://blusher.us-east.host.bsky.network","createdAt":"2025-10-03T08:08:03.334Z"},{"url":"https://cordyceps.us-west.host.bsky.network","createdAt":"2025-10-03T08:04:14.985Z"},{"url":"https://velvetfoot.us-east.host.bsky.network","createdAt":"2025-10-03T08:02:28.145Z"},{"url":"https://brittlegill.us-west.host.bsky.network","createdAt":"2025-10-03T07:57:17.629Z"},{"url":"https://puffball.us-east.host.bsky.network","createdAt":"2025-10-03T07:55:56.908Z"},{"url":"https://button.us-west.host.bsky.network","createdAt":"2025-10-03T07:55:50.240Z"},{"url":"https://matsutake.us-west.host.bsky.network","createdAt":"2025-10-03T07:53:04.111Z"},{"url":"https://splitgill.us-east.host.bsky.network","createdAt":"2025-10-03T07:50:48.671Z"},{"url":"https://earthstar.us-east.host.bsky.network","createdAt":"2025-10-03T07:47:20.389Z"},{"url":"https://magic.us-west.host.bsky.network","createdAt":"2025-10-03T07:46:11.022Z"},{"url":"https://lepista.us-west.host.bsky.network","createdAt":"2025-10-03T07:38:30.980Z"},{"url":"https://amanita.us-east.host.bsky.network","createdAt":"2025-10-03T07:33:12.640Z"},{"url":"https://stinkhorn.us-west.host.bsky.network","createdAt":"2025-10-03T07:33:06.118Z"},{"url":"https://bracket.us-west.host.bsky.network","createdAt":"2025-10-03T07:20:15.581Z"},{"url":"https://shaggymane.us-west.host.bsky.network","createdAt":"2025-10-03T07:13:41.304Z"},{"url":"https://milkcap.us-west.host.bsky.network","createdAt":"2025-10-03T07:10:58.306Z"},{"url":"https://enoki.us-east.host.bsky.network","createdAt":"2025-10-03T07:07:50.429Z"},{"url":"https://chaga.us-west.host.bsky.network","createdAt":"2025-10-03T07:07:30.769Z"},{"url":"https://panthercap.us-east.host.bsky.network","createdAt":"2025-10-03T07:01:22.260Z"},{"url":"https://inkcap.us-east.host.bsky.network","createdAt":"2025-10-03T07:01:16.096Z"},{"url":"https://yellowfoot.us-west.host.bsky.network","createdAt":"2025-10-03T06:56:21.765Z"},{"url":"https://psathyrella.us-west.host.bsky.network","createdAt":"2025-10-03T06:46:37.273Z"},{"url":"https://woodear.us-west.host.bsky.network","createdAt":"2025-10-03T06:40:52.412Z"},{"url":"https://cremini.us-west.host.bsky.network","createdAt":"2025-10-03T06:28:36.173Z"},{"url":"https://scalycap.us-west.host.bsky.network","createdAt":"2025-10-03T06:06:31.730Z"},{"url":"https://woodtuft.us-west.host.bsky.network","createdAt":"2025-10-03T05:58:23.576Z"},{"url":"https://rooter.us-west.host.bsky.network","createdAt":"2025-10-03T05:56:06.132Z"},{"url":"https://scarletina.us-east.host.bsky.network","createdAt":"2025-10-03T05:44:19.393Z"},{"url":"https://blewit.us-west.host.bsky.network","createdAt":"2025-10-03T05:31:28.934Z"},{"url":"https://elfcup.us-east.host.bsky.network","createdAt":"2025-10-03T05:27:54.337Z"},{"url":"https://grisette.us-west.host.bsky.network","createdAt":"2025-10-03T05:26:31.359Z"},{"url":"https://witchesbutter.us-west.host.bsky.network","createdAt":"2025-10-03T05:15:26.216Z"},{"url":"https://shimeji.us-east.host.bsky.network","createdAt":"2025-10-03T05:13:09.906Z"},{"url":"https://mottlegill.us-west.host.bsky.network","createdAt":"2025-10-03T04:59:55.842Z"},{"url":"https://goldenear.us-west.host.bsky.network","createdAt":"2025-10-03T04:44:02.535Z"},{"url":"https://russula.us-west.host.bsky.network","createdAt":"2025-10-03T04:28:18.708Z"},{"url":"https://suillus.us-west.host.bsky.network","createdAt":"2025-10-03T04:25:28.916Z"},{"url":"https://truffle.us-east.host.bsky.network","createdAt":"2025-10-03T04:10:54.674Z"},{"url":"https://poisonpie.us-west.host.bsky.network","createdAt":"2025-10-03T04:05:33.845Z"},{"url":"https://coral.us-east.host.bsky.network","createdAt":"2025-10-03T04:03:01.332Z"},{"url":"https://boletus.us-west.host.bsky.network","createdAt":"2025-10-03T03:35:30.431Z"},{"url":"https://pds.trump.com","createdAt":"2025-10-03T09:26:22.015Z","alive":false},{"url":"https://blacksky.app","createdAt":"2025-10-03T09:13:17.149Z","alive":true,"inviteCodeRequired":false,"phoneVerificationRequired":false},{"url":"https://pds.monke.moe","createdAt":"2025-10-03T09:09:33.929Z","alive":true,"inviteCodeRequired":true,"phoneVerificationRequired":false},{"url":"https://tngl.sh","createdAt":"2025-10-03T09:04:55.760Z","alive":true,"inviteCodeRequired":true,"phoneVerificationRequired":false},{"url":"https://atproto.brid.gy","createdAt":"2025-10-03T08:57:08.236Z","alive":true,"inviteCodeRequired":false,"phoneVerificationRequired":false},{"url":"https://at.app.wafrn.net","createdAt":"2025-10-03T08:56:01.661Z","alive":true,"inviteCodeRequired":true,"phoneVerificationRequired":false},{"url":"https://pds.witchcraft.systems","createdAt":"2025-10-03T08:45:13.970Z","alive":true,"inviteCodeRequired":true,"phoneVerificationRequired":false},{"url":"https://bsky.kazto.net","createdAt":"2025-10-03T08:37:01.453Z","alive":true,"inviteCodeRequired":true,"phoneVerificationRequired":false},{"url":"https://social.farrant.me","createdAt":"2025-10-03T07:33:13.134Z","alive":true,"inviteCodeRequired":true,"phoneVerificationRequired":false},{"url":"https://keik.info","createdAt":"2025-10-03T07:29:46.964Z","alive":true,"inviteCodeRequired":true,"phoneVerificationRequired":false},{"url":"https://pds.lenooby09.tech","createdAt":"2025-10-03T07:26:42.625Z","alive":true,"inviteCodeRequired":true,"phoneVerificationRequired":false},{"url":"https://pds.synth.download","createdAt":"2025-10-03T07:14:04.628Z","alive":true,"inviteCodeRequired":true,"phoneVerificationRequired":false},{"url":"https://at.jazco.dev","createdAt":"2025-10-03T06:42:45.167Z","alive":true,"inviteCodeRequired":true,"phoneVerificationRequired":false},{"url":"https://northsky.social","createdAt":"2025-10-03T06:39:09.114Z","alive":true,"inviteCodeRequired":true,"phoneVerificationRequired":false},{"url":"https://pds.tributaries.digital","createdAt":"2025-10-03T05:28:51.316Z","alive":true,"inviteCodeRequired":true,"phoneVerificationRequired":false},{"url":"https://si46.homes","createdAt":"2025-10-03T03:43:26.964Z","alive":true,"inviteCodeRequired":true,"phoneVerificationRequired":false}]}