{"startedAt":"2025-02-06T03:06:42.856Z","endpoints":[{"url":"https://elfcup.us-east.host.bsky.network","createdAt":"2025-02-06T09:42:17.172Z"},{"url":"https://grisette.us-west.host.bsky.network","createdAt":"2025-02-06T09:42:12.173Z"},{"url":"https://goldenear.us-west.host.bsky.network","createdAt":"2025-02-06T09:42:06.477Z"},{"url":"https://pioppino.us-west.host.bsky.network","createdAt":"2025-02-06T09:42:05.974Z"},{"url":"https://polypore.us-west.host.bsky.network","createdAt":"2025-02-06T09:42:05.614Z"},{"url":"https://mycena.us-west.host.bsky.network","createdAt":"2025-02-06T09:41:58.328Z"},{"url":"https://dapperling.us-west.host.bsky.network","createdAt":"2025-02-06T09:41:56.638Z"},{"url":"https://suillus.us-west.host.bsky.network","createdAt":"2025-02-06T09:41:49.474Z"},{"url":"https://mottlegill.us-west.host.bsky.network","createdAt":"2025-02-06T09:41:47.408Z"},{"url":"https://waxcap.us-west.host.bsky.network","createdAt":"2025-02-06T09:41:46.802Z"},{"url":"https://rooter.us-west.host.bsky.network","createdAt":"2025-02-06T09:41:42.433Z"},{"url":"https://lionsmane.us-east.host.bsky.network","createdAt":"2025-02-06T09:38:57.184Z"},{"url":"https://brittlegill.us-west.host.bsky.network","createdAt":"2025-02-06T09:38:30.017Z"},{"url":"https://scarletina.us-east.host.bsky.network","createdAt":"2025-02-06T09:38:21.687Z"},{"url":"https://poisonpie.us-west.host.bsky.network","createdAt":"2025-02-06T09:38:13.289Z"},{"url":"https://reishi.us-east.host.bsky.network","createdAt":"2025-02-06T09:37:33.649Z"},{"url":"https://boletus.us-west.host.bsky.network","createdAt":"2025-02-06T09:37:24.319Z"},{"url":"https://woodtuft.us-west.host.bsky.network","createdAt":"2025-02-06T09:37:01.837Z"},{"url":"https://cremini.us-west.host.bsky.network","createdAt":"2025-02-06T09:35:54.290Z"},{"url":"https://enoki.us-east.host.bsky.network","createdAt":"2025-02-06T09:35:42.527Z"},{"url":"https://morel.us-east.host.bsky.network","createdAt":"2025-02-06T09:33:44.443Z"},{"url":"https://witchesbutter.us-west.host.bsky.network","createdAt":"2025-02-06T09:33:07.502Z"},{"url":"https://stinkhorn.us-west.host.bsky.network","createdAt":"2025-02-06T09:31:54.196Z"},{"url":"https://helvella.us-east.host.bsky.network","createdAt":"2025-02-06T09:31:24.710Z"},{"url":"https://button.us-west.host.bsky.network","createdAt":"2025-02-06T09:31:12.609Z"},{"url":"https://puffball.us-east.host.bsky.network","createdAt":"2025-02-06T09:31:08.400Z"},{"url":"https://panthercap.us-east.host.bsky.network","createdAt":"2025-02-06T09:29:44.636Z"},{"url":"https://blusher.us-east.host.bsky.network","createdAt":"2025-02-06T09:27:22.412Z"},{"url":"https://cordyceps.us-west.host.bsky.network","createdAt":"2025-02-06T09:27:14.137Z"},{"url":"https://shaggymane.us-west.host.bsky.network","createdAt":"2025-02-06T09:26:54.163Z"},{"url":"https://amanita.us-east.host.bsky.network","createdAt":"2025-02-06T09:26:38.843Z"},{"url":"https://fibercap.us-west.host.bsky.network","createdAt":"2025-02-06T09:24:37.717Z"},{"url":"https://velvetfoot.us-east.host.bsky.network","createdAt":"2025-02-06T09:23:35.961Z"},{"url":"https://woodear.us-west.host.bsky.network","createdAt":"2025-02-06T09:22:40.344Z"},{"url":"https://ganoderma.us-west.host.bsky.network","createdAt":"2025-02-06T09:20:08.876Z"},{"url":"https://lepista.us-west.host.bsky.network","createdAt":"2025-02-06T09:17:36.776Z"},{"url":"https://verpa.us-west.host.bsky.network","createdAt":"2025-02-06T09:16:52.553Z"},{"url":"https://shimeji.us-east.host.bsky.network","createdAt":"2025-02-06T09:16:20.472Z"},{"url":"https://earthstar.us-east.host.bsky.network","createdAt":"2025-02-06T09:14:10.415Z"},{"url":"https://milkcap.us-west.host.bsky.network","createdAt":"2025-02-06T09:09:34.245Z"},{"url":"https://bracket.us-west.host.bsky.network","createdAt":"2025-02-06T09:04:08.353Z"},{"url":"https://lobster.us-east.host.bsky.network","createdAt":"2025-02-06T08:59:49.166Z"},{"url":"https://porcini.us-east.host.bsky.network","createdAt":"2025-02-06T08:55:00.220Z"},{"url":"https://agaric.us-west.host.bsky.network","createdAt":"2025-02-06T08:51:16.999Z"},{"url":"https://chaga.us-west.host.bsky.network","createdAt":"2025-02-06T08:50:27.548Z"},{"url":"https://matsutake.us-west.host.bsky.network","createdAt":"2025-02-06T08:49:05.356Z"},{"url":"https://inkcap.us-east.host.bsky.network","createdAt":"2025-02-06T08:42:58.965Z"},{"url":"https://shiitake.us-east.host.bsky.network","createdAt":"2025-02-06T08:35:13.800Z"},{"url":"https://yellowfoot.us-west.host.bsky.network","createdAt":"2025-02-06T08:34:12.928Z"},{"url":"https://scalycap.us-west.host.bsky.network","createdAt":"2025-02-06T08:30:24.345Z"},{"url":"https://oyster.us-east.host.bsky.network","createdAt":"2025-02-06T08:18:27.516Z"},{"url":"https://conocybe.us-west.host.bsky.network","createdAt":"2025-02-06T08:07:14.308Z"},{"url":"https://meadow.us-east.host.bsky.network","createdAt":"2025-02-06T08:06:10.232Z"},{"url":"https://chanterelle.us-west.host.bsky.network","createdAt":"2025-02-06T08:04:12.073Z"},{"url":"https://hydnum.us-west.host.bsky.network","createdAt":"2025-02-06T08:00:14.582Z"},{"url":"https://parasol.us-east.host.bsky.network","createdAt":"2025-02-06T07:52:39.070Z"},{"url":"https://truffle.us-east.host.bsky.network","createdAt":"2025-02-06T07:48:57.877Z"},{"url":"https://magic.us-west.host.bsky.network","createdAt":"2025-02-06T07:46:40.303Z"},{"url":"https://oysterling.us-west.host.bsky.network","createdAt":"2025-02-06T07:41:29.627Z"},{"url":"https://splitgill.us-east.host.bsky.network","createdAt":"2025-02-06T07:31:22.772Z"},{"url":"https://blewit.us-west.host.bsky.network","createdAt":"2025-02-06T07:27:59.998Z"},{"url":"https://coral.us-east.host.bsky.network","createdAt":"2025-02-06T06:55:12.814Z"},{"url":"https://maitake.us-west.host.bsky.network","createdAt":"2025-02-06T06:42:15.391Z"},{"url":"https://gomphus.us-west.host.bsky.network","createdAt":"2025-02-06T06:41:40.562Z"},{"url":"https://russula.us-west.host.bsky.network","createdAt":"2025-02-06T05:32:04.100Z"},{"url":"https://bicke.nl","createdAt":"2025-02-06T09:30:19.857Z","alive":true,"inviteCodeRequired":true,"phoneVerificationRequired":false},{"url":"https://stmediaserver.site","createdAt":"2025-02-06T09:27:23.050Z","alive":false},{"url":"https://atproto.brid.gy","createdAt":"2025-02-06T09:22:05.376Z","alive":true,"inviteCodeRequired":false,"phoneVerificationRequired":false},{"url":"https://social.kabcash.com","createdAt":"2025-02-06T08:40:40.450Z","alive":true,"inviteCodeRequired":true,"phoneVerificationRequired":false},{"url":"https://known.directory","createdAt":"2025-02-06T08:40:35.898Z","alive":false},{"url":"https://crsocial.site","createdAt":"2025-02-06T08:04:20.836Z","alive":true,"inviteCodeRequired":true,"phoneVerificationRequired":false},{"url":"https://social.chnwth.online","createdAt":"2025-02-06T07:10:23.305Z","alive":true,"inviteCodeRequired":true,"phoneVerificationRequired":false},{"url":"https://stuartmiller.dev","createdAt":"2025-02-06T06:52:05.833Z","alive":true,"inviteCodeRequired":true,"phoneVerificationRequired":false},{"url":"https://klatch.app","createdAt":"2025-02-06T06:29:39.454Z","alive":false},{"url":"https://social.jkei.club","createdAt":"2025-02-06T06:17:11.080Z","alive":true,"inviteCodeRequired":true,"phoneVerificationRequired":false},{"url":"https://bsky.dix.sexy","createdAt":"2025-02-06T04:56:56.075Z","alive":true,"inviteCodeRequired":true,"phoneVerificationRequired":false},{"url":"https://pds.aisociety.com","createdAt":"2025-02-06T04:38:05.781Z","alive":false},{"url":"https://pds.onloft.dev","createdAt":"2025-02-06T04:38:04.048Z","alive":false},{"url":"https://nvll.xyz","createdAt":"2025-02-06T04:24:33.229Z","alive":true,"inviteCodeRequired":true,"phoneVerificationRequired":false},{"url":"https://rsky.ripperoni.com","createdAt":"2025-02-06T03:53:39.167Z","alive":true,"inviteCodeRequired":true,"phoneVerificationRequired":false}]}