{"startedAt":"2026-06-20T04:35:00.906Z","endpoints":[{"url":"https://rhizopogon.us-west.host.bsky.network","createdAt":"2026-06-20T07:04:00.160Z"},{"url":"https://brittlegill.us-west.host.bsky.network","createdAt":"2026-06-20T07:03:57.158Z"},{"url":"https://chalciporus.us-west.host.bsky.network","createdAt":"2026-06-20T07:03:50.781Z"},{"url":"https://auriporia.us-west.host.bsky.network","createdAt":"2026-06-20T07:03:45.341Z"},{"url":"https://phellinus.us-west.host.bsky.network","createdAt":"2026-06-20T07:03:43.329Z"},{"url":"https://discina.us-west.host.bsky.network","createdAt":"2026-06-20T07:03:30.999Z"},{"url":"https://enoki.us-east.host.bsky.network","createdAt":"2026-06-20T07:03:23.231Z"},{"url":"https://poisonpie.us-west.host.bsky.network","createdAt":"2026-06-20T07:03:22.162Z"},{"url":"https://fibercap.us-west.host.bsky.network","createdAt":"2026-06-20T07:03:14.977Z"},{"url":"https://matsutake.us-west.host.bsky.network","createdAt":"2026-06-20T07:00:44.463Z"},{"url":"https://stropharia.us-west.host.bsky.network","createdAt":"2026-06-20T07:00:12.896Z"},{"url":"https://puffball.us-east.host.bsky.network","createdAt":"2026-06-20T07:00:07.060Z"},{"url":"https://conocybe.us-west.host.bsky.network","createdAt":"2026-06-20T06:56:31.339Z"},{"url":"https://leccinum.us-west.host.bsky.network","createdAt":"2026-06-20T06:53:03.711Z"},{"url":"https://helvella.us-east.host.bsky.network","createdAt":"2026-06-20T06:51:59.205Z"},{"url":"https://inkcap.us-east.host.bsky.network","createdAt":"2026-06-20T06:51:18.959Z"},{"url":"https://bankera.us-west.host.bsky.network","createdAt":"2026-06-20T06:47:39.795Z"},{"url":"https://dapperling.us-west.host.bsky.network","createdAt":"2026-06-20T06:45:52.925Z"},{"url":"https://polypore.us-west.host.bsky.network","createdAt":"2026-06-20T06:40:38.175Z"},{"url":"https://reishi.us-east.host.bsky.network","createdAt":"2026-06-20T06:40:31.507Z"},{"url":"https://jellybaby.us-east.host.bsky.network","createdAt":"2026-06-20T06:39:56.613Z"},{"url":"https://chaga.us-west.host.bsky.network","createdAt":"2026-06-20T06:39:24.247Z"},{"url":"https://button.us-west.host.bsky.network","createdAt":"2026-06-20T06:36:28.090Z"},{"url":"https://shimeji.us-east.host.bsky.network","createdAt":"2026-06-20T06:34:40.286Z"},{"url":"https://witchesbutter.us-west.host.bsky.network","createdAt":"2026-06-20T06:29:07.330Z"},{"url":"https://coral.us-east.host.bsky.network","createdAt":"2026-06-20T06:29:06.580Z"},{"url":"https://calocybe.us-west.host.bsky.network","createdAt":"2026-06-20T06:27:53.271Z"},{"url":"https://lionsmane.us-east.host.bsky.network","createdAt":"2026-06-20T06:16:33.040Z"},{"url":"https://agrocybe.us-west.host.bsky.network","createdAt":"2026-06-20T06:16:23.335Z"},{"url":"https://shiitake.us-east.host.bsky.network","createdAt":"2026-06-20T06:11:20.805Z"},{"url":"https://gomphidius.us-west.host.bsky.network","createdAt":"2026-06-20T06:07:37.666Z"},{"url":"https://rooter.us-west.host.bsky.network","createdAt":"2026-06-20T05:54:54.445Z"},{"url":"https://psathyrella.us-west.host.bsky.network","createdAt":"2026-06-20T05:52:43.147Z"},{"url":"https://panthercap.us-east.host.bsky.network","createdAt":"2026-06-20T05:48:01.735Z"},{"url":"https://bracket.us-west.host.bsky.network","createdAt":"2026-06-20T05:36:10.874Z"},{"url":"https://porcini.us-east.host.bsky.network","createdAt":"2026-06-20T05:32:16.531Z"},{"url":"https://hygrophorus.us-west.host.bsky.network","createdAt":"2026-06-20T05:28:34.260Z"},{"url":"https://ganoderma.us-west.host.bsky.network","createdAt":"2026-06-20T05:24:58.756Z"},{"url":"https://amanita.us-east.host.bsky.network","createdAt":"2026-06-20T05:16:42.278Z"},{"url":"https://woodear.us-west.host.bsky.network","createdAt":"2026-06-20T05:15:00.006Z"},{"url":"https://oyster.us-east.host.bsky.network","createdAt":"2026-06-20T05:12:54.898Z"},{"url":"https://hollowfoot.us-west.host.bsky.network","createdAt":"2026-06-20T05:12:34.663Z"},{"url":"https://blewit.us-west.host.bsky.network","createdAt":"2026-06-20T05:02:36.754Z"},{"url":"https://cortinarius.us-west.host.bsky.network","createdAt":"2026-06-20T04:48:12.416Z"},{"url":"https://oysterling.us-west.host.bsky.network","createdAt":"2026-06-20T04:36:47.259Z"},{"url":"https://lepista.us-west.host.bsky.network","createdAt":"2026-06-20T04:35:28.640Z"},{"url":"https://pds.trump.com","createdAt":"2026-06-20T07:04:10.446Z","alive":false},{"url":"https://pds.federdeck.com","createdAt":"2026-06-20T07:03:50.383Z","alive":false},{"url":"https://bbi.to","createdAt":"2026-06-20T07:03:46.560Z","alive":true,"inviteCodeRequired":false,"phoneVerificationRequired":false},{"url":"https://fmpds.cacheblasters.com","createdAt":"2026-06-20T07:03:44.501Z","alive":true,"inviteCodeRequired":false,"phoneVerificationRequired":false},{"url":"https://pds.1095.me","createdAt":"2026-06-20T07:03:15.147Z","alive":true,"inviteCodeRequired":false,"phoneVerificationRequired":false},{"url":"https://pds.polymarket.social","createdAt":"2026-06-20T07:00:41.265Z","alive":true,"inviteCodeRequired":false,"phoneVerificationRequired":false},{"url":"https://eurosky.social","createdAt":"2026-06-20T06:59:34.591Z","alive":true,"inviteCodeRequired":false,"phoneVerificationRequired":true},{"url":"https://pds.wsocial.network","createdAt":"2026-06-20T06:56:21.435Z","alive":true,"inviteCodeRequired":true,"phoneVerificationRequired":false},{"url":"https://pds.authority-one.com","createdAt":"2026-06-20T06:47:35.771Z","alive":true,"inviteCodeRequired":true,"phoneVerificationRequired":false},{"url":"https://u.jalsa.world","createdAt":"2026-06-20T06:35:43.187Z","alive":true,"inviteCodeRequired":true,"phoneVerificationRequired":false},{"url":"https://knot1.tangled.sh","createdAt":"2026-06-20T06:24:14.019Z","alive":false},{"url":"https://pds.zimbatm.com","createdAt":"2026-06-20T06:20:24.351Z","alive":true,"inviteCodeRequired":true,"phoneVerificationRequired":false},{"url":"https://haruhwa.com","createdAt":"2026-06-20T06:07:40.985Z","alive":true,"inviteCodeRequired":false,"phoneVerificationRequired":false},{"url":"https://atproto.brid.gy","createdAt":"2026-06-20T06:03:14.435Z","alive":true,"inviteCodeRequired":false,"phoneVerificationRequired":false},{"url":"https://tngl.sh","createdAt":"2026-06-20T05:40:16.515Z","alive":true,"inviteCodeRequired":true,"phoneVerificationRequired":false},{"url":"https://pds.astra.lgbt","createdAt":"2026-06-20T05:38:47.769Z","alive":true,"inviteCodeRequired":true,"phoneVerificationRequired":false},{"url":"https://blacksky.app","createdAt":"2026-06-20T05:10:03.398Z","alive":true,"inviteCodeRequired":false,"phoneVerificationRequired":true},{"url":"https://northsky.social","createdAt":"2026-06-20T05:09:12.205Z","alive":true,"inviteCodeRequired":true,"phoneVerificationRequired":false},{"url":"https://dev.pds.konastat.com","createdAt":"2026-06-20T04:57:02.487Z","alive":true,"inviteCodeRequired":true,"phoneVerificationRequired":false},{"url":"https://keik.info","createdAt":"2026-06-20T04:48:59.499Z","alive":true,"inviteCodeRequired":true,"phoneVerificationRequired":false},{"url":"https://pds.random-encounter.gay","createdAt":"2026-06-20T04:36:02.399Z","alive":false}]}