{"startedAt":"2025-07-11T03:32:23.735Z","endpoints":[{"url":"https://pholiota.us-west.host.bsky.network","createdAt":"2025-07-11T10:05:57.620Z"},{"url":"https://leccinum.us-west.host.bsky.network","createdAt":"2025-07-11T10:05:38.479Z"},{"url":"https://bankera.us-west.host.bsky.network","createdAt":"2025-07-11T10:05:37.398Z"},{"url":"https://hygrophorus.us-west.host.bsky.network","createdAt":"2025-07-11T10:05:18.296Z"},{"url":"https://cortinarius.us-west.host.bsky.network","createdAt":"2025-07-11T10:05:16.843Z"},{"url":"https://hebeloma.us-west.host.bsky.network","createdAt":"2025-07-11T10:05:15.683Z"},{"url":"https://calocybe.us-west.host.bsky.network","createdAt":"2025-07-11T10:05:00.077Z"},{"url":"https://agrocybe.us-west.host.bsky.network","createdAt":"2025-07-11T10:04:50.326Z"},{"url":"https://entoloma.us-west.host.bsky.network","createdAt":"2025-07-11T10:04:41.521Z"},{"url":"https://gomphidius.us-west.host.bsky.network","createdAt":"2025-07-11T10:03:42.994Z"},{"url":"https://puffball.us-east.host.bsky.network","createdAt":"2025-07-11T10:01:13.156Z"},{"url":"https://splitgill.us-east.host.bsky.network","createdAt":"2025-07-11T10:01:07.585Z"},{"url":"https://shaggymane.us-west.host.bsky.network","createdAt":"2025-07-11T09:59:36.481Z"},{"url":"https://milkcap.us-west.host.bsky.network","createdAt":"2025-07-11T09:54:47.377Z"},{"url":"https://fibercap.us-west.host.bsky.network","createdAt":"2025-07-11T09:53:15.562Z"},{"url":"https://ganoderma.us-west.host.bsky.network","createdAt":"2025-07-11T09:51:51.934Z"},{"url":"https://enoki.us-east.host.bsky.network","createdAt":"2025-07-11T09:51:36.932Z"},{"url":"https://hydnum.us-west.host.bsky.network","createdAt":"2025-07-11T09:46:59.434Z"},{"url":"https://woodtuft.us-west.host.bsky.network","createdAt":"2025-07-11T09:41:05.995Z"},{"url":"https://morel.us-east.host.bsky.network","createdAt":"2025-07-11T09:39:51.508Z"},{"url":"https://helvella.us-east.host.bsky.network","createdAt":"2025-07-11T09:38:57.580Z"},{"url":"https://oysterling.us-west.host.bsky.network","createdAt":"2025-07-11T09:37:16.182Z"},{"url":"https://woodear.us-west.host.bsky.network","createdAt":"2025-07-11T09:34:50.246Z"},{"url":"https://panus.us-west.host.bsky.network","createdAt":"2025-07-11T09:26:18.218Z"},{"url":"https://blewit.us-west.host.bsky.network","createdAt":"2025-07-11T09:23:46.013Z"},{"url":"https://psathyrella.us-west.host.bsky.network","createdAt":"2025-07-11T09:21:29.503Z"},{"url":"https://oyster.us-east.host.bsky.network","createdAt":"2025-07-11T09:17:02.497Z"},{"url":"https://mazegill.us-west.host.bsky.network","createdAt":"2025-07-11T09:16:37.595Z"},{"url":"https://fuzzyfoot.us-west.host.bsky.network","createdAt":"2025-07-11T09:16:28.289Z"},{"url":"https://shiitake.us-east.host.bsky.network","createdAt":"2025-07-11T09:15:45.877Z"},{"url":"https://shimeji.us-east.host.bsky.network","createdAt":"2025-07-11T09:14:15.159Z"},{"url":"https://blusher.us-east.host.bsky.network","createdAt":"2025-07-11T09:13:15.687Z"},{"url":"https://lionsmane.us-east.host.bsky.network","createdAt":"2025-07-11T09:11:22.657Z"},{"url":"https://lobster.us-east.host.bsky.network","createdAt":"2025-07-11T09:10:02.806Z"},{"url":"https://scalycap.us-west.host.bsky.network","createdAt":"2025-07-11T09:02:49.364Z"},{"url":"https://dapperling.us-west.host.bsky.network","createdAt":"2025-07-11T09:02:18.376Z"},{"url":"https://porcini.us-east.host.bsky.network","createdAt":"2025-07-11T09:01:27.376Z"},{"url":"https://russula.us-west.host.bsky.network","createdAt":"2025-07-11T08:57:54.465Z"},{"url":"https://gomphus.us-west.host.bsky.network","createdAt":"2025-07-11T08:48:41.334Z"},{"url":"https://meadow.us-east.host.bsky.network","createdAt":"2025-07-11T08:44:01.536Z"},{"url":"https://cordyceps.us-west.host.bsky.network","createdAt":"2025-07-11T08:43:48.460Z"},{"url":"https://verpa.us-west.host.bsky.network","createdAt":"2025-07-11T08:43:12.806Z"},{"url":"https://elfcup.us-east.host.bsky.network","createdAt":"2025-07-11T08:42:40.805Z"},{"url":"https://mottlegill.us-west.host.bsky.network","createdAt":"2025-07-11T08:38:55.410Z"},{"url":"https://cremini.us-west.host.bsky.network","createdAt":"2025-07-11T08:29:29.067Z"},{"url":"https://conocybe.us-west.host.bsky.network","createdAt":"2025-07-11T08:21:40.487Z"},{"url":"https://brittlegill.us-west.host.bsky.network","createdAt":"2025-07-11T08:20:36.764Z"},{"url":"https://grisette.us-west.host.bsky.network","createdAt":"2025-07-11T08:10:14.818Z"},{"url":"https://agaric.us-west.host.bsky.network","createdAt":"2025-07-11T08:08:02.131Z"},{"url":"https://lepista.us-west.host.bsky.network","createdAt":"2025-07-11T08:03:47.885Z"},{"url":"https://pioppino.us-west.host.bsky.network","createdAt":"2025-07-11T07:58:24.695Z"},{"url":"https://chaga.us-west.host.bsky.network","createdAt":"2025-07-11T07:51:53.113Z"},{"url":"https://poisonpie.us-west.host.bsky.network","createdAt":"2025-07-11T07:39:23.969Z"},{"url":"https://goldenear.us-west.host.bsky.network","createdAt":"2025-07-11T07:33:36.112Z"},{"url":"https://truffle.us-east.host.bsky.network","createdAt":"2025-07-11T07:26:19.908Z"},{"url":"https://boletus.us-west.host.bsky.network","createdAt":"2025-07-11T07:10:24.906Z"},{"url":"https://rooter.us-west.host.bsky.network","createdAt":"2025-07-11T07:05:28.747Z"},{"url":"https://inkcap.us-east.host.bsky.network","createdAt":"2025-07-11T07:01:01.288Z"},{"url":"https://panthercap.us-east.host.bsky.network","createdAt":"2025-07-11T06:54:35.144Z"},{"url":"https://button.us-west.host.bsky.network","createdAt":"2025-07-11T06:44:45.216Z"},{"url":"https://reishi.us-east.host.bsky.network","createdAt":"2025-07-11T06:28:36.707Z"},{"url":"https://coral.us-east.host.bsky.network","createdAt":"2025-07-11T06:17:07.985Z"},{"url":"https://witchesbutter.us-west.host.bsky.network","createdAt":"2025-07-11T06:16:58.507Z"},{"url":"https://polypore.us-west.host.bsky.network","createdAt":"2025-07-11T06:06:38.586Z"},{"url":"https://parasol.us-east.host.bsky.network","createdAt":"2025-07-11T05:59:05.136Z"},{"url":"https://yellowfoot.us-west.host.bsky.network","createdAt":"2025-07-11T05:41:23.293Z"},{"url":"https://hollowfoot.us-west.host.bsky.network","createdAt":"2025-07-11T05:10:28.509Z"},{"url":"https://matsutake.us-west.host.bsky.network","createdAt":"2025-07-11T05:09:59.278Z"},{"url":"https://mycena.us-west.host.bsky.network","createdAt":"2025-07-11T05:08:36.251Z"},{"url":"https://amanita.us-east.host.bsky.network","createdAt":"2025-07-11T04:56:16.722Z"},{"url":"https://suillus.us-west.host.bsky.network","createdAt":"2025-07-11T04:49:12.448Z"},{"url":"https://bracket.us-west.host.bsky.network","createdAt":"2025-07-11T04:48:21.979Z"},{"url":"https://magic.us-west.host.bsky.network","createdAt":"2025-07-11T04:44:54.096Z"},{"url":"https://waxcap.us-west.host.bsky.network","createdAt":"2025-07-11T04:15:38.880Z"},{"url":"https://maitake.us-west.host.bsky.network","createdAt":"2025-07-11T03:47:41.300Z"},{"url":"https://pds.trump.com","createdAt":"2025-07-11T10:06:00.811Z","alive":false},{"url":"https://atproto.brid.gy","createdAt":"2025-07-11T09:57:24.845Z","alive":true,"inviteCodeRequired":false,"phoneVerificationRequired":false},{"url":"https://at.app.wafrn.net","createdAt":"2025-07-11T08:09:13.854Z","alive":true,"inviteCodeRequired":true,"phoneVerificationRequired":false},{"url":"https://keik.info","createdAt":"2025-07-11T07:13:56.312Z","alive":true,"inviteCodeRequired":true,"phoneVerificationRequired":false},{"url":"https://pds.sprk.so","createdAt":"2025-07-11T07:12:16.869Z","alive":true,"inviteCodeRequired":false,"phoneVerificationRequired":false},{"url":"https://yeet.fm","createdAt":"2025-07-11T06:05:17.225Z","alive":true,"inviteCodeRequired":true,"phoneVerificationRequired":false},{"url":"https://pds.epaphrodit.us","createdAt":"2025-07-11T05:10:06.230Z","alive":true,"inviteCodeRequired":true,"phoneVerificationRequired":false},{"url":"https://pds.chrisbriant.uk","createdAt":"2025-07-11T04:16:49.964Z","alive":true,"inviteCodeRequired":true,"phoneVerificationRequired":false}]}